{
  "ToDo": [

    {
      "id": "0",
      "caption": "Lorem ipsum dolor sit amet",
      "cover": "https://pmtips.net/Portals/0/EasyDNNNews/2137/700600p546EDNmainimg-3-types-of-tools-for-project-task-management1.jpg",
      "isCompleted": true
    },
    {
      "id": "1",
      "caption": "Lorem ipsum dolor sit amet, consectetur adipiscing elit, sed do eiusmod tempor incididunt ut labore et dolore magna aliqua.",
      "cover": "https://eosc.eu/sites/default/files/2021-08/eosc_task_forces_community.jpg",
      "isCompleted": true
    },
    {
      "id": "2",
      "caption": "Lorem ipsum dolor sit amet, consectetur adipiscing elit",
      "cover": "https://plainenglish.com/wp-content/uploads/expressions/up-to-the-task.png",
      "isCompleted": false
    },
    {
      "id": "3",
      "caption": "Lorem ipsum dolor sit amet, consectetur adipiscing elit, sed do eiusmod tempor incididunt ut labore et dolore magna aliqua.",
      "cover": "https://blog.definedlearning.com/hubfs/PBL%20Performance%20Task%20.jpeg",
      "isCompleted": true
    },
    {
      "id": "4",
      "caption": "sed do eiusmod",
      "cover": "https://www.theedadvocate.org/wp-content/uploads/2019/05/CR1-660x400.jpg",
      "isCompleted": false
    }

  ],
  "InProgress": [
    {
      "id": "5",
      "caption": "Lorem ipsum dolor sit amet",
      "cover": "https://i2.wp.com/www.additudemag.com/wp-content/uploads/2021/11/GettyImages-1138022429-1.jpg?resize=1280%2C720px&ssl=1",
      "isCompleted": true
    },
    {
      "id": "6",
      "caption": "sed do eiusmod",
      "cover": "https://www.theworkathomewoman.com/wp-content/uploads/20-short-task-websites-1024x684.jpg",
      "isCompleted": false
    }
  ],
  "Done": [

    {
      "id": "7",
      "caption": "Lorem ipsum dolor sit amet, consectetur adipiscing elit, sed do eiusmod tempor incididunt ut labore et dolore magna aliqua.",
      "cover": "https://louiscarter.com/wp-content/uploads/2020/09/task-oriented-leadership-v1.jpg",
      "isCompleted": true
    },
    {
      "id": "8",
      "caption": "Lorem ipsum dolor sit amet, consectetur adipiscing elit",
      "cover": "https://static1.makeuseofimages.com/wordpress/wp-content/uploads/2020/09/GoogleTasksAppList-iPhone.jpg?q=50&fit=contain&w=750&h=375&dpr=1.5",
      "isCompleted": false
    },
    {
      "id": "9",
      "caption": "Lorem ipsum dolor sit amet, consectetur adipiscing elit, sed do eiusmod tempor incididunt ut labore et dolore magna aliqua.",
      "cover": "https://cdn.eteknix.com/wp-content/uploads/2019/07/1-88.jpg",
      "isCompleted": true
    }
  ]
}
